xcompare/__init__.py
xcompare/mom.py
xcompare/plot.py
xcompare/xcompare.py
xcompare/xr_stats.py
xcompare-2.0.1.dist-info/LICENSE.txt
xcompare-2.0.1.dist-info/METADATA
xcompare-2.0.1.dist-info/WHEEL
xcompare-2.0.1.dist-info/top_level.txt
xcompare-2.0.1.dist-info/RECORD
